spynnaker/__init__.py
spynnaker/_version.py
spynnaker/py.typed
spynnaker/spike_checker.py
spynnaker/spynnaker_plotting.py
spynnaker/pyNN/__init__.py
spynnaker/pyNN/_version.py
spynnaker/pyNN/config_setup.py
spynnaker/pyNN/exceptions.py
spynnaker/pyNN/random_distribution.py
spynnaker/pyNN/setup_pynn.py
spynnaker/pyNN/spinnaker.py
spynnaker/pyNN/spynnaker.cfg
spynnaker/pyNN/spynnaker_external_device_plugin_manager.py
spynnaker/pyNN/types.py
spynnaker/pyNN/connections/__init__.py
spynnaker/pyNN/connections/ethernet_command_connection.py
spynnaker/pyNN/connections/ethernet_control_connection.py
spynnaker/pyNN/connections/spif_live_spikes_connection.py
spynnaker/pyNN/connections/spynnaker_live_spikes_connection.py
spynnaker/pyNN/connections/spynnaker_poisson_control_connection.py
spynnaker/pyNN/data/__init__.py
spynnaker/pyNN/data/spynnaker_data_view.py
spynnaker/pyNN/data/spynnaker_data_writer.py
spynnaker/pyNN/external_devices/__init__.py
spynnaker/pyNN/external_devices_models/__init__.py
spynnaker/pyNN/external_devices_models/abstract_ethernet_controller.py
spynnaker/pyNN/external_devices_models/abstract_ethernet_sensor.py
spynnaker/pyNN/external_devices_models/abstract_ethernet_translator.py
spynnaker/pyNN/external_devices_models/abstract_multicast_controllable_device.py
spynnaker/pyNN/external_devices_models/arbitrary_fpga_device.py
spynnaker/pyNN/external_devices_models/external_device_lif_control.py
spynnaker/pyNN/external_devices_models/external_device_lif_control_vertex.py
spynnaker/pyNN/external_devices_models/external_spinnaker_link_fpga_retina_device.py
spynnaker/pyNN/external_devices_models/icub_retina_device.py
spynnaker/pyNN/external_devices_models/machine_munich_motor_device.py
spynnaker/pyNN/external_devices_models/munich_spinnaker_link_motor_device.py
spynnaker/pyNN/external_devices_models/munich_spinnaker_link_retina_device.py
spynnaker/pyNN/external_devices_models/spif_devices.py
spynnaker/pyNN/external_devices_models/spif_input_device.py
spynnaker-1!7.4.0.dist-info/licenses/LICENSE
spynnaker-1!7.4.0.dist-info/licenses/LICENSE_POLICY.md
spynnaker-1!7.4.0.dist-info/METADATA
spynnaker-1!7.4.0.dist-info/WHEEL
spynnaker-1!7.4.0.dist-info/top_level.txt
spynnaker-1!7.4.0.dist-info/zip-safe
spynnaker-1!7.4.0.dist-info/RECORD
