Metadata-Version: 2.4
Name: sPyNNaker
Version: 1!7.4.0
Summary: Tools for simulating neural models generated using PyNN on the SpiNNaker platform
Home-page: https://github.com/SpiNNakerManchester/SpyNNaker
Maintainer: SpiNNakerTeam
Maintainer-email: spinnakerusers@googlegroups.com
License: Apache-2.0
Keywords: spinnaker,pynn
Classifier: Development Status :: 5 - Production/Stable
Classifier: Intended Audience :: Developers
Classifier: Intended Audience :: Science/Research
Classifier: Natural Language :: English
Classifier: Operating System :: POSIX :: Linux
Classifier: Operating System :: Microsoft :: Windows
Classifier: Operating System :: MacOS
Classifier: Programming Language :: Python :: 3
Classifier: Programming Language :: Python :: 3.8
Classifier: Programming Language :: Python :: 3.9
Classifier: Programming Language :: Python :: 3.10
Classifier: Programming Language :: Python :: 3.11
Classifier: Programming Language :: Python :: 3.12
Classifier: Programming Language :: Python :: 3.13
Requires-Python: <4,>=3.8
License-File: LICENSE
License-File: LICENSE_POLICY.md
Requires-Dist: SpiNNFrontEndCommon==1!7.4.0
Requires-Dist: quantities
Requires-Dist: pynn!=0.12.0,>=0.11
Requires-Dist: neo
Requires-Dist: lazyarray
Requires-Dist: csa
Provides-Extra: test
Requires-Dist: SpiNNakerTestBase==1!7.4.0; extra == "test"
Requires-Dist: pytest-cov; extra == "test"
Requires-Dist: testfixtures; extra == "test"
Requires-Dist: mock; extra == "test"
Requires-Dist: graphviz; extra == "test"
Requires-Dist: types-requests; extra == "test"
Dynamic: license-file
